yolov5/benchmarks.py
yolov5/detect.py
yolov5/export.py
yolov5/hubconf.py
yolov5/train.py
yolov5/val.py
celldetec_pack-0.0.0.dist-info/METADATA
celldetec_pack-0.0.0.dist-info/WHEEL
celldetec_pack-0.0.0.dist-info/top_level.txt
celldetec_pack-0.0.0.dist-info/RECORD
