Metadata-Version: 2.1
Name: celldetec-pack
Version: 0.0.0
Summary: Cell phone detection
Requires-Python: >=3.6
Requires-Dist: requirements.txt
